waf_middleware/__init__.py
waf_middleware/blacklist.txt
waf_middleware/firewall.py
waf_middleware/firewall_upgraded.py
waf_middleware/malicious_hashes.txt
waf_middleware/rules.json
waf_middleware/tor_ips.txt
waf_middleware_hoaithoai35-1.1.9.dist-info/METADATA
waf_middleware_hoaithoai35-1.1.9.dist-info/WHEEL
waf_middleware_hoaithoai35-1.1.9.dist-info/top_level.txt
waf_middleware_hoaithoai35-1.1.9.dist-info/RECORD
