Metadata-Version: 2.1
Name: waf-middleware-hoaithoai35
Version: 1.1.9
Summary: A powerful WAF Middleware for Flask with SQLi, XSS, and Logic protection
Home-page: https://github.com/HoaiThoai/waf-middleware
Author: Nguyen Hoai Thoai
Author-email: hoaithoai35@gmail.com
Classifier: Programming Language :: Python :: 3
Classifier: License :: OSI Approved :: MIT License
Classifier: Operating System :: OS Independent
Requires-Python: >=3.6
Requires-Dist: Flask>=2.0.0
Requires-Dist: requests>=2.25.0
